ndcube/__init__.py
ndcube/_version.py
ndcube/conftest.py
ndcube/global_coords.py
ndcube/meta.py
ndcube/ndcollection.py
ndcube/ndcube.py
ndcube/ndcube_sequence.py
ndcube/version.py
ndcube/data/README.rst
ndcube/extra_coords/__init__.py
ndcube/extra_coords/extra_coords.py
ndcube/extra_coords/table_coord.py
ndcube/extra_coords/tests/__init__.py
ndcube/extra_coords/tests/test_extra_coords.py
ndcube/extra_coords/tests/test_lookup_table_coord.py
ndcube/mixins/__init__.py
ndcube/mixins/ndslicing.py
ndcube/tests/__init__.py
ndcube/tests/helpers.py
ndcube/tests/test_global_coords.py
ndcube/tests/test_meta.py
ndcube/tests/test_ndcollection.py
ndcube/tests/test_ndcube.py
ndcube/tests/test_ndcubesequence.py
ndcube/utils/__init__.py
ndcube/utils/collection.py
ndcube/utils/cube.py
ndcube/utils/exceptions.py
ndcube/utils/misc.py
ndcube/utils/sequence.py
ndcube/utils/wcs.py
ndcube/utils/sphinx/__init__.py
ndcube/utils/sphinx/code_context.py
ndcube/utils/tests/__init__.py
ndcube/utils/tests/test_utils_collection.py
ndcube/utils/tests/test_utils_cube.py
ndcube/utils/tests/test_utils_sequence.py
ndcube/utils/tests/test_utils_wcs.py
ndcube/visualization/__init__.py
ndcube/visualization/base.py
ndcube/visualization/descriptor.py
ndcube/visualization/mpl_plotter.py
ndcube/visualization/mpl_sequence_plotter.py
ndcube/visualization/plotting_utils.py
ndcube/visualization/tests/__init__.py
ndcube/visualization/tests/figure_hashes_mpl_3100_ft_261_astropy_710_animators_124.json
ndcube/visualization/tests/figure_hashes_mpl_dev_ft_261_astropy_dev_animators_dev.json
ndcube/visualization/tests/test_plotting.py
ndcube/visualization/tests/test_plotting_utils.py
ndcube/wcs/__init__.py
ndcube/wcs/tools.py
ndcube/wcs/tests/__init__.py
ndcube/wcs/tests/test_tools.py
ndcube/wcs/wrappers/__init__.py
ndcube/wcs/wrappers/compound_wcs.py
ndcube/wcs/wrappers/reordered_wcs.py
ndcube/wcs/wrappers/resampled_wcs.py
ndcube/wcs/wrappers/tests/__init__.py
ndcube/wcs/wrappers/tests/conftest.py
ndcube-2.3.5.dist-info/licenses/LICENSE.rst
ndcube-2.3.5.dist-info/METADATA
ndcube-2.3.5.dist-info/WHEEL
ndcube-2.3.5.dist-info/top_level.txt
ndcube-2.3.5.dist-info/RECORD
