Metadata-Version: 2.4
Name: ndcube
Version: 2.3.5
Summary: A package for multi-dimensional contiguous and non-contiguous coordinate aware arrays.
Author-email: The SunPy Community <sunpy@googlegroups.com>
License: Copyright (c) 2024, The SunPy Community
Project-URL: Homepage, https://docs.sunpy.org/projects/ndcube
Project-URL: Source Code, https://github.com/sunpy/ndcube
Project-URL: Download, https://pypi.org/project/ndcube
Project-URL: Documentation, https://docs.sunpy.org/projects/ndcube
Project-URL: Changelog, https://docs.sunpy.org/projects/ndcube/en/stable/whatsnew/changelog.html
Project-URL: Issue Tracker, https://github.com/sunpy/ndcube/issues
Requires-Python: >=3.10
License-File: LICENSE.rst
Requires-Dist: astropy!=5.1.0,>=5.0.6
Requires-Dist: gwcs>=0.18
Requires-Dist: numpy>=1.23.0
Requires-Dist: scipy>=1.8.0
Provides-Extra: tests
Requires-Dist: dask; extra == "tests"
Requires-Dist: pytest-astropy; extra == "tests"
Requires-Dist: pytest-cov; extra == "tests"
Requires-Dist: pytest-doctestplus; extra == "tests"
Requires-Dist: pytest-mpl>=0.12; extra == "tests"
Requires-Dist: pytest-xdist; extra == "tests"
Requires-Dist: pytest; extra == "tests"
Requires-Dist: pytest-memray; sys_platform != "win32" and extra == "tests"
Requires-Dist: scipy; extra == "tests"
Requires-Dist: specutils; extra == "tests"
Requires-Dist: sunpy>=5.0.0; extra == "tests"
Provides-Extra: docs
Requires-Dist: sphinx; extra == "docs"
Requires-Dist: sphinx-automodapi; extra == "docs"
Requires-Dist: sunpy-sphinx-theme; extra == "docs"
Requires-Dist: packaging; extra == "docs"
Requires-Dist: matplotlib; extra == "docs"
Requires-Dist: mpl-animators>=1.0; extra == "docs"
Requires-Dist: sphinx-changelog>=1.1.0; extra == "docs"
Requires-Dist: sphinx-gallery; extra == "docs"
Requires-Dist: sphinxext-opengraph; extra == "docs"
Requires-Dist: sunpy>=5.0.0; extra == "docs"
Provides-Extra: plotting
Requires-Dist: matplotlib>=3.5.0; extra == "plotting"
Requires-Dist: mpl_animators>=1.0; extra == "plotting"
Provides-Extra: reproject
Requires-Dist: reproject>=0.7.1; extra == "reproject"
Provides-Extra: all
Requires-Dist: ndcube[plotting,reproject]; extra == "all"
Provides-Extra: dev
Requires-Dist: ndcube[docs,plotting,reproject,tests]; extra == "dev"
Dynamic: license-file
